MANIFEST.in
README.rst
setup.py
pyupnp_async/__init__.py
pyupnp_async/const.py
pyupnp_async/device.py
pyupnp_async/error.py
pyupnp_async/upnp.py
pyupnp_async.egg-info/PKG-INFO
pyupnp_async.egg-info/SOURCES.txt
pyupnp_async.egg-info/dependency_links.txt
pyupnp_async.egg-info/requires.txt
pyupnp_async.egg-info/top_level.txt
pyupnp_async/service/__init__.py
pyupnp_async/service/base_service.py
pyupnp_async/service/factory.py
pyupnp_async/service/wan_common_interface_config.py
pyupnp_async/service/wan_ip_connection.py
pyupnp_async/service/wan_ppp_connection.py
tests/__init__.py
tests/context.py
tests/test_upnp_soup_error.py