Metadata-Version: 1.0
Name: pyupnp-async
Version: 0.1.1.0
Summary: Python Library for UPnP operations using asyncio
Home-page: https://github.com/xinhuang/pyupnp-async
Author: Xin Huang
Author-email: xinhuang.abc@gmail.com
License: License :: OSI Approved :: MIT License
Platform: UNKNOWN
